premium_primitives/__init__.py
premium_primitives/country_code_to_continent.py
premium_primitives/country_code_to_income.py
premium_primitives/country_code_to_population.py
premium_primitives/diversity_score.py
premium_primitives/latlong_to_city.py
premium_primitives/latlong_to_countrycode.py
premium_primitives/latlong_to_county.py
premium_primitives/latlong_to_state.py
premium_primitives/lsa.py
premium_primitives/mean_characters_per_sentence.py
premium_primitives/number_of_sentences.py
premium_primitives/part_of_speech_count.py
premium_primitives/phone_number_to_area.py
premium_primitives/phone_number_to_country.py
premium_primitives/polarity_score.py
premium_primitives/postalcode_to_latlong.py
premium_primitives/postalcode_to_per_capita_income.py
premium_primitives/postalcode_to_state.py
premium_primitives/stopword_count.py
premium_primitives/sub_region_code_to_median_household_income.py
premium_primitives/sub_region_code_to_per_capita_income.py
premium_primitives/sub_region_code_to_region.py
premium_primitives/utils.py
premium_primitives/version.py
premium_primitives/data/GNI_per_capita.csv
premium_primitives/data/census_regions.csv
premium_primitives/data/country_to_continent.csv
premium_primitives/data/postalcode_to_latlong_data_allCountries.txt
premium_primitives/data/postalcode_to_per_capita_income_data.csv
premium_primitives/data/sub_region_code_to_median_household_income_data.csv
premium_primitives/data/sub_region_code_to_per_capita_income_data.csv
premium_primitives/data/nltk_data/corpora/gutenberg/austen-emma.txt
premium_primitives/data/nltk_data/corpora/gutenberg/austen-persuasion.txt
premium_primitives/data/nltk_data/corpora/gutenberg/austen-sense.txt
premium_primitives/data/nltk_data/corpora/gutenberg/bible-kjv.txt
premium_primitives/data/nltk_data/corpora/gutenberg/blake-poems.txt
premium_primitives/data/nltk_data/corpora/gutenberg/bryant-stories.txt
premium_primitives/data/nltk_data/corpora/gutenberg/burgess-busterbrown.txt
premium_primitives-0.1.0.dist-info/METADATA
premium_primitives-0.1.0.dist-info/WHEEL
premium_primitives-0.1.0.dist-info/entry_points.txt
premium_primitives-0.1.0.dist-info/top_level.txt
premium_primitives-0.1.0.dist-info/RECORD
