Metadata-Version: 2.1
Name: premium_primitives
Version: 0.1.0
Author-email: "Alteryx, Inc." <open_source_support@alteryx.com>
Maintainer-email: "Alteryx, Inc." <open_source_support@alteryx.com>
License: BSD 3-clause
Project-URL: Documentation, https://featuretools.alteryx.com
Project-URL: Source Code, https://github.com/alteryx/premium_primitives/
Project-URL: Changes, https://github.com/alteryx/premium_primitives/blob/main/release_notes.rst
Project-URL: Issue Tracker, https://github.com/alteryx/premium_primitives/issues
Project-URL: Twitter, https://twitter.com/alteryxoss
Project-URL: Chat, https://join.slack.com/t/alteryx-oss/shared_invite/zt-182tyvuxv-NzIn6eiCEf8TBziuKp0bNA
Keywords: feature engineering,data science,machine learning
Classifier: Development Status :: 5 - Production/Stable
Classifier: Intended Audience :: Science/Research
Classifier: Intended Audience :: Developers
Classifier: Topic :: Software Development
Classifier: Topic :: Scientific/Engineering
Classifier: Programming Language :: Python
Classifier: Programming Language :: Python :: 3
Classifier: Programming Language :: Python :: 3.9
Classifier: Programming Language :: Python :: 3.10
Classifier: Programming Language :: Python :: 3.11
Classifier: Programming Language :: Python :: 3.12
Classifier: Operating System :: Microsoft :: Windows
Classifier: Operating System :: POSIX
Classifier: Operating System :: Unix
Classifier: Operating System :: MacOS
Requires-Python: <4,>=3.9
Requires-Dist: numpy >=1.21.0
Requires-Dist: pandas >=1.5.0
Requires-Dist: featuretools >=1.5.0
Requires-Dist: woodwork >=0.8.1
Requires-Dist: nltk >=3.4.5
Requires-Dist: scikit-learn >=0.20.0
Requires-Dist: phone-iso3166 >=0.3
Requires-Dist: phonenumbers >=8.10.6
Requires-Dist: reverse-geocoder >=1.5.1
Requires-Dist: zipcodes >=1.0.5
Provides-Extra: dev
Requires-Dist: ruff >=0.0.239 ; extra == 'dev'
Requires-Dist: black[jupyter] >=23.1.0 ; extra == 'dev'
Requires-Dist: pre-commit >=2.20.0 ; extra == 'dev'
Requires-Dist: premium-primitives[test] ; extra == 'dev'
Provides-Extra: test
Requires-Dist: pip >=22.0.2 ; extra == 'test'
Requires-Dist: pytest >=7.1.2 ; extra == 'test'
Requires-Dist: pytest-xdist >=2.5.0 ; extra == 'test'
Requires-Dist: pytest-cov >=3.0.0 ; extra == 'test'
